YamlSchemaAgent/__init__.py
YamlSchemaAgent/entry_point.py
YamlSchemaAgent/generate.py
YamlSchemaAgent/logger.py
YamlSchemaAgent/schema_types.py
YamlSchemaAgent/tags_pkg.py
YamlSchemaAgent/validation.py
yaml_schema_agent-0.2.1a0.dist-info/METADATA
yaml_schema_agent-0.2.1a0.dist-info/WHEEL
yaml_schema_agent-0.2.1a0.dist-info/entry_points.txt
yaml_schema_agent-0.2.1a0.dist-info/top_level.txt
yaml_schema_agent-0.2.1a0.dist-info/RECORD
