Metadata-Version: 2.1
Name: yaml-schema-agent
Version: 0.2.1a0
Summary: Project to Generate Schema from/to YAML and Also Validate
Home-page: https://github.com/nayak-swastik/yaml-schema-agent
Author: Swastik.Nayak
Author-email: swastik.nayak.eu@gmail.com
Requires-Dist: jsonschema
